xrcalc/__init__.py
xrcalc/main.py
xrcalc-0.1.6.dist-info/LICENSE
xrcalc-0.1.6.dist-info/METADATA
xrcalc-0.1.6.dist-info/WHEEL
xrcalc-0.1.6.dist-info/entry_points.txt
xrcalc-0.1.6.dist-info/top_level.txt
xrcalc-0.1.6.dist-info/RECORD
